lin/__init__.py
lin/interfaces/__init__.py
lin/interfaces/peak/LinBus.py
lin/interfaces/peak/PLinApi.py
lin/interfaces/peak/__init__.py
lin/interfaces/vector/__init__.py
python_lin-0.1.1.dist-info/LICENSE
python_lin-0.1.1.dist-info/METADATA
python_lin-0.1.1.dist-info/WHEEL
python_lin-0.1.1.dist-info/top_level.txt
python_lin-0.1.1.dist-info/RECORD
